threadingwebdriver/__init__.py
threadingwebdriver-0.0.3.dist-info/METADATA
threadingwebdriver-0.0.3.dist-info/WHEEL
threadingwebdriver-0.0.3.dist-info/licenses/LICENSE
threadingwebdriver-0.0.3.dist-info/RECORD
