Metadata-Version: 2.1
Name: threadingwebdriver
Version: 0.0.3
Summary: Selenium webdriver using thread pool. (Chrome only now.)
Project-URL: Homepage, https://github.com/chorong8883/threadingwebdriver
Author-email: Chor <chorong8883@gmail.com>
License-File: LICENSE
Classifier: License :: OSI Approved :: MIT License
Classifier: Operating System :: POSIX :: Linux
Classifier: Programming Language :: Python :: 3.10
Requires-Python: >=3.10
Requires-Dist: selenium>=4.14
